kmins/__init__.py
kmins/kmins.py
kmins-0.0.1.dist-info/METADATA
kmins-0.0.1.dist-info/WHEEL
kmins-0.0.1.dist-info/top_level.txt
kmins-0.0.1.dist-info/RECORD
