Metadata-Version: 2.1
Name: kmins
Version: 0.0.1
Summary: K-Means algorithm from scratch.
Author: Ismael Sandoval, Mauricio Ponce
Author-email: ismael.sandoval.aguilar@gmail.com, maupon2004@gmail.com
Keywords: python,k-means,clustering
Classifier: Development Status :: 1 - Planning
Classifier: Intended Audience :: Developers
Classifier: Programming Language :: Python :: 3
Classifier: Operating System :: Unix
Classifier: Operating System :: MacOS :: MacOS X
Classifier: Operating System :: Microsoft :: Windows
Requires-Dist: pandas
Requires-Dist: numpy
Requires-Dist: scikit-learn
